{
    "title": "WD Purple Surveillance Storage Interview",
    "description": "The smart choice for surveillance<br \/>\n<br \/>\nWD Purple Surveillance Storage offers exclusive AllFrame\u2122 technology to bring you premium reliability and peace-of-mind when installing your home or small to medium business security system. Exclusive firmware upgrades work with ATA streaming to reduce error pixilation and video interruptions that occur when desktop hard drives are incorrectly used as storage in security systems. WD Purple Surveillance Storage is built for 24\/7, always-on, high-definition surveillance security systems that use up to eight hard drives and up to 32 cameras. <br \/>\n<br \/>\nImprove performance with AllFrame\n\u2022 Works with ATA streaming to reduce frame loss and improves playback<br \/>\n\u2022 Specifically tuned for surveillance security systems<br \/>\n\u2022 Caching algorithms are tuned for write-intensive, low bit rate, high stream count applications <br \/>\n\u2022 Priority change for write allocations and preemptive caching policies <br \/>\n\u2022 TLER ATA streaming support <br \/>\n\u2022 Supports up to eight drives<br \/>",
    "referenceId": "ea778cf11e4617eeddeb70b104b44291",
    "date_created": "1440115200",
    "date_modified": "1455787152",
    "tags": "WD,Western,Digital,Purple,WD40PURX,4TB,SATA,Hard,Drive,WD30PURX,3TB,6.0Gb\/s,Hard Drive,Newegg,Newegg.com,Newegg TV,NeweggTV,review,technology,video,electronics,deals,shop,unboxing,overview,product tour,computer",
    "sourceId": "6",
    "VIDEO_LENGTH": "LONG",
    "status": "approved",
    "video_type": "interviews",
    "video_category": "storage",
    "age_gate": "no",
    "video_brand": "western_digital",
    "visibility": "1",
    "video_description": null,
    "featured_category": null,
    "VV_VI": "28",
    "CVV_VI": "6",
    "engagement_score": null,
    "conversion_score": null,
    "id": "7638944",
    "loginId": "1758381",
    "entityType": "1",
    "sortOrder": "14",
    "entityIdParent": "65648628",
    "titleTextEncoded": "WD-Purple-Surveillance-Storage-Interview",
    "category": "",
    "duration": 854,
    "settings": null,
    "asset": {
        "user": {
            "firstName": "",
            "lastName": "",
            "emailAddress": ""
        },
        "videoMeta": {
            "duration": "854",
            "width": 1920,
            "height": 1080
        },
        "mediaDuration": "854",
        "thumbnailUrl": "\/\/do0631budpzeh.cloudfront.net\/live\/users\/1758381\/canvas\/655\/368\/850514816-021280719.jpg",
        "type": "mp4",
        "dashUrl": "\/\/d2mhchrq41duh4.cloudfront.net\/1758381\/7638944\/69143a\/media.mpd",
        "hlsUrl": "\/\/d2mhchrq41duh4.cloudfront.net\/1758381\/7638944\/69143a\/media.m3u8",
        "sources": [
            {
                "file": "\/\/d2mhchrq41duh4.cloudfront.net\/1758381\/7638944\/69143\/1080p_media.mp4",
                "quality": "1080p",
                "mime": "video\/mp4",
                "width": 1920,
                "height": 1080
            },
            {
                "file": "\/\/d2mhchrq41duh4.cloudfront.net\/1758381\/7638944\/69143\/720p_media.mp4",
                "quality": "720p",
                "mime": "video\/mp4",
                "width": 1280,
                "height": 720
            },
            {
                "file": "\/\/d2mhchrq41duh4.cloudfront.net\/1758381\/7638944\/69143\/480p_media.mp4",
                "quality": "480p",
                "mime": "video\/mp4",
                "width": 854,
                "height": 480,
                "tvpdefault": true
            },
            {
                "file": "\/\/d2mhchrq41duh4.cloudfront.net\/1758381\/7638944\/69143\/360p_media.mp4",
                "quality": "360p",
                "mime": "video\/mp4",
                "width": 640,
                "height": 360
            },
            {
                "file": "\/\/d2mhchrq41duh4.cloudfront.net\/1758381\/7638944\/69143\/240p_media.mp4",
                "quality": "240p",
                "mime": "video\/mp4",
                "width": 320,
                "height": 180
            },
            {
                "file": "\/\/d2mhchrq41duh4.cloudfront.net\/1758381\/7638944\/144p_cc5a9_WD_Purple_Surveillance_Storage_Interview_-_Newegg_TV.mp4",
                "quality": "144p",
                "mime": "video\/mp4",
                "width": 256,
                "height": 144
            }
        ],
        "prettyDuration": "00:14:14"
    },
    "transcripts": null,
    "metrics_statistics": {
        "VV_VI": {
            "lastUpdatedDate": "2017-05-17",
            "engagement_score": {
                "lastUpdatedDate": "2017-05-17"
            }
        },
        "CVV_VI": {
            "lastUpdatedDate": "2017-05-17",
            "conversion_score": {
                "lastUpdatedDate": "2017-05-17"
            }
        }
    }
}